conf_generator/__init__.py
conf_generator/conf_generator.py
conf_generator-1.0.1.dist-info/METADATA
conf_generator-1.0.1.dist-info/WHEEL
conf_generator-1.0.1.dist-info/top_level.txt
conf_generator-1.0.1.dist-info/RECORD
