Metadata-Version: 2.1
Name: conf-generator
Version: 1.0.1
Summary: Conf-Generator is a tool for specifying and exploring hyper-parameters sets in Machine Learning pipelines defined through configuration files.
Home-page: https://github.com/nicolaspi/conf_generator
Author: Nicolas Pinchaud
Author-email: nicolas.pinchaud@gmail.com
License: UNKNOWN
Platform: UNKNOWN
Classifier: Programming Language :: Python :: 3
Classifier: Operating System :: OS Independent
Requires-Python: >=3.6
Requires-Dist: pyyaml
